duprequests/__init__.py
duprequests/middleware.py
duprequests/tests.py
django_duprequests-0.1.5.dist-info/LICENSE
django_duprequests-0.1.5.dist-info/METADATA
django_duprequests-0.1.5.dist-info/WHEEL
django_duprequests-0.1.5.dist-info/top_level.txt
django_duprequests-0.1.5.dist-info/RECORD
