Metadata-Version: 2.1
Name: django-duprequests
Version: 0.1.5
Summary: Drop duplicated requests
Home-page: https://github.com/CraveFood/django-duprequests
Author: Sergio Oliveira
Author-email: seocam@seocam.com
License: BSD
Platform: UNKNOWN
Classifier: Development Status :: 3 - Alpha
Classifier: Intended Audience :: Developers
Classifier: Topic :: Software Development :: Libraries :: Python Modules
Classifier: License :: OSI Approved :: BSD License
Classifier: Environment :: Web Environment
Classifier: Framework :: Django
Classifier: Programming Language :: Python :: 2
Classifier: Programming Language :: Python :: 3
Requires-Dist: Django
